brio/__init__.py
brio/bias/BiasDetector.py
brio/bias/FreqVsFreqBiasDetector.py
brio/bias/FreqVsRefBiasDetector.py
brio/bias/KLDivergence.py
brio/bias/TotalVariationDistance.py
brio/bias/__init__.py
brio/bias/threshold_calculator.py
brio/data_processing/Preprocessing.py
brio/data_processing/__init__.py
brio/ml_models/BinaryClassificationTraining.py
brio/ml_models/Training.py
brio/ml_models/__init__.py
brio/opacity/__init__.py
brio/risks/__init__.py
brio/utils/Preprocessing.py
brio/utils/__init__.py
brio/utils/funcs.py
brio-1.1.0.dist-info/METADATA
brio-1.1.0.dist-info/WHEEL
brio-1.1.0.dist-info/top_level.txt
brio-1.1.0.dist-info/zip-safe
brio-1.1.0.dist-info/RECORD
