Metadata-Version: 2.1
Name: brio
Version: 1.1.0
Summary: Brio
Home-page: https://github.com/DLBD-Department/BRIO_x_Alkemy/
Author: DLBDDepartment@alkemy.com
License: MIT
Project-URL: Bug Tracker, https://github.com/DLBD-Department/BRIO_x_Alkemy/issues
Project-URL: Source Code, https://github.com/DLBD-Department/BRIO_x_Alkemy
Keywords: brio
Platform: any
Classifier: Intended Audience :: Developers
Classifier: License :: OSI Approved :: MIT License
Classifier: Operating System :: OS Independent
Classifier: Programming Language :: Python
Classifier: Topic :: Software Development :: Libraries :: Python Modules
Classifier: Programming Language :: Python :: 3.10
Classifier: Programming Language :: Python :: 3.11
Requires-Python: >=3.10
Provides-Extra: test
Requires-Dist: pytest ; extra == 'test'
